{"name":"Shattered","password":"YKFZ","required_chips":0,"time_limit":95,"map":{"width":30,"height":25,"data":[0,0,0,0,2,2,2,2,2,2,2,0,0,0,0,0,0,0,0,0,0,0,0,0,0,0,0,0,0,0,0,0,0,0,2,2,2,2,2,2,2,0,0,0,2,2,2,2,2,2,2,2,2,2,2,0,0,0,0,0,2,2,2,2,2,2,3,4,2,2,2,0,0,0,2,2,2,2,2,2,2,2,2,2,2,0,0,0,0,0,2,2,2,2,2,2,5,1,1,2,2,0,0,0,2,2,6,6,6,6,6,6,7,2,2,2,2,2,0,0,2,2,1,1,2,1,5,8,1,2,2,2,2,2,2,2,9,2,2,2,2,2,10,2,2,2,2,2,0,0,2,2,1,1,11,12,1,13,13,2,2,2,2,2,2,2,9,2,2,2,14,2,10,2,15,2,2,2,0,0,2,2,1,5,1,2,5,10,12,1,4,2,2,2,2,2,9,2,2,2,1,2,16,2,1,17,2,2,0,0,2,2,2,18,1,2,5,2,1,2,1,2,10,17,6,6,9,2,10,10,1,6,7,2,19,2,2,2,0,0,2,2,2,2,20,2,1,5,5,1,5,2,20,2,2,2,2,2,10,2,10,2,5,21,1,2,2,2,0,0,2,2,2,2,5,2,10,2,1,2,1,1,12,13,13,13,1,1,1,10,1,22,23,2,15,2,2,2,0,0,0,0,2,2,5,2,1,1,12,2,12,2,2,24,10,10,10,2,19,2,10,2,2,2,1,2,2,2,2,2,0,0,2,2,7,2,2,2,25,1,26,1,2,27,2,2,2,2,2,2,28,2,2,2,1,2,2,2,2,2,0,0,2,2,6,6,6,6,9,2,29,1,1,1,6,6,7,2,30,29,27,29,30,20,1,30,1,29,2,2,0,0,2,2,2,2,2,2,2,2,2,20,2,27,2,2,7,2,2,27,29,27,2,2,27,2,27,2,2,2,0,0,2,2,2,2,2,2,2,2,31,25,30,1,30,30,29,2,2,1,30,1,2,2,29,30,11,1,2,2,0,0,0,0,0,0,0,0,2,2,2,2,30,27,2,2,7,2,2,1,32,1,2,2,27,2,2,27,2,2,0,0,0,0,0,0,0,0,2,2,2,2,30,27,2,2,7,2,30,30,27,30,30,2,1,1,30,1,29,2,0,0,0,0,0,0,0,0,0,0,2,2,30,27,27,27,7,2,30,27,1,27,30,2,2,29,2,2,2,2,0,0,0,0,0,0,0,0,0,0,2,2,30,30,30,30,9,2,30,30,27,30,30,2,2,2,2,2,2,2,0,0,0,0,0,0,0,0,0,0,2,2,2,2,2,2,24,2,2,30,30,30,2,2,2,2,2,2,2,2,0,0,0,0,0,0,0,0,0,0,2,2,2,2,2,2,12,2,2,2,16,2,2,2,2,2,0,0,0,0,0,0,0,0,0,0,0,0,0,0,0,0,0,2,2,3,1,5,1,13,1,12,1,1,2,2,0,0,0,0,0,0,0,0,0,0,0,0,0,0,0,0,0,2,2,18,1,23,5,1,12,11,1,1,2,2,0,0,0,0,0,0,0,0,0,0,0,0,0,0,0,0,0,2,2,2,2,2,2,2,2,2,2,2,2,2,0,0,0,0,0,0,0,0,0,0,0,0,0,0,0,0,0,2,2,2,2,2,2,2,2,2,2,2,2,2,0,0,0,0],"legend":["Blank","Floor","Wall","IceNW","IceNE","Ice","ForceE","ForceS","IceSE","ForceN","RecessedWall","ThinWallW","Water","ThinWallS","BrownButton","Teleport","BlueLock","RedButton","IceSW","CloneBlockN","GreenLock","Fire","BearTrap","ForceW","YellowLock","ThinWallE","ThinWallSE","ToggleFloor","RedLock","GreenButton","ToggleWall","Exit","ThinWallN"]},"entities":[{"kind":"Player","pos":[20,9]},{"kind":"Block","pos":[3,5]},{"kind":"Block","pos":[20,6]},{"kind":"Block","pos":[8,7]},{"kind":"Block","pos":[9,8]},{"kind":"Block","pos":[8,9]},{"kind":"Block","pos":[11,12]},{"kind":"Block","pos":[18,21]},{"kind":"Block","pos":[20,21]},{"kind":"Block","pos":[22,21]},{"kind":"FireBoots","pos":[13,12]},{"kind":"IceSkates","pos":[20,9]},{"kind":"BlueKey","pos":[9,11]},{"kind":"BlueKey","pos":[20,17]},{"kind":"RedKey","pos":[20,7]},{"kind":"GreenKey","pos":[6,10]},{"kind":"YellowKey","pos":[11,11]},{"kind":"YellowKey","pos":[23,22]}],"connections":[{"src":[24,9],"dest":[24,5]},{"src":[24,5],"dest":[24,9]},{"src":[20,5],"dest":[21,9]},{"src":[25,6],"dest":[18,10]},{"src":[13,7],"dest":[24,7]}]}