{"name":"Hobgoblins and Chimera","author":"Tyrethali Ansrath","password":"ERJB","seed":540581484,"required_chips":4,"time_limit":250,"map":{"width":25,"height":31,"data":[2,2,2,2,2,2,2,2,2,2,2,2,3,2,2,2,2,2,2,2,2,2,2,2,2,2,2,2,2,2,2,2,2,2,2,2,2,1,2,2,2,2,2,2,2,2,2,2,2,2,2,2,2,2,1,1,1,1,1,1,1,1,1,1,1,1,1,1,1,1,1,2,2,2,2,2,2,2,2,1,2,2,2,2,2,2,2,2,2,2,2,2,2,2,2,1,2,2,2,2,2,2,2,2,1,2,2,2,2,4,1,1,1,1,1,5,2,2,2,2,1,2,2,2,2,2,2,2,2,1,2,2,2,2,1,2,2,6,2,2,1,2,2,2,2,1,2,2,2,2,2,2,2,4,7,5,2,2,2,1,2,1,1,1,2,1,2,2,2,4,7,5,2,2,2,2,2,2,7,4,1,1,1,1,8,2,1,1,1,2,9,1,1,1,1,5,7,2,2,2,2,2,2,9,1,2,2,2,2,2,2,1,1,1,2,2,2,2,2,2,1,8,2,2,2,2,2,2,2,1,2,10,1,1,1,2,2,11,2,2,1,1,1,10,2,1,2,2,2,2,2,2,2,2,1,2,1,1,1,1,12,13,11,13,1,1,1,1,1,2,1,2,2,2,2,2,2,2,2,1,2,1,1,1,1,1,13,11,13,1,1,1,1,1,2,1,2,2,2,2,2,4,1,1,8,2,1,1,1,1,1,13,11,13,1,1,1,1,1,2,9,1,1,5,2,2,1,2,2,2,2,2,1,1,1,1,13,11,13,1,1,1,12,2,2,2,2,2,1,2,2,1,2,1,1,1,2,13,13,13,13,11,11,11,13,13,13,13,2,1,1,1,2,1,2,2,1,6,1,1,1,11,11,11,11,11,11,1,11,11,11,11,11,11,1,1,1,6,1,2,2,1,2,1,1,1,2,13,13,13,13,11,11,11,13,13,13,13,2,1,1,1,2,1,2,2,1,2,2,2,2,2,12,1,1,1,13,11,13,1,1,1,1,2,2,2,2,2,1,2,2,9,1,1,5,2,1,1,1,1,1,13,11,13,1,1,1,1,1,2,4,1,1,8,2,2,2,2,2,1,2,1,1,1,1,1,13,11,13,1,1,1,1,1,2,1,2,2,2,2,2,2,2,2,1,2,1,1,1,1,1,13,11,13,12,1,1,1,1,2,1,2,2,2,2,2,2,2,2,1,2,10,1,1,1,2,2,11,2,2,1,1,1,10,2,1,2,2,2,2,2,2,2,4,1,2,2,2,2,2,2,1,1,1,2,2,2,2,2,2,1,5,2,2,2,2,2,2,7,9,1,1,1,1,5,2,1,1,1,2,4,1,1,1,1,8,7,2,2,2,2,2,2,9,7,8,2,2,2,1,2,1,1,1,2,1,2,2,2,9,7,8,2,2,2,2,2,2,2,1,2,2,2,2,1,2,2,6,2,2,1,2,2,2,2,1,2,2,2,2,2,2,2,2,1,2,2,2,2,9,1,1,1,1,1,8,2,2,2,2,1,2,2,2,2,2,2,2,2,1,2,2,2,2,2,2,2,2,2,2,2,2,2,2,2,1,2,2,2,2,2,2,2,2,1,1,1,1,1,1,1,1,1,1,1,1,1,1,1,1,1,2,2,2,2,2,2,2,2,2,2,2,2,2,2,2,2,1,2,2,2,2,2,2,2,2,2,2,2,2,2,2,2,2,2,2,2,2,2,2,2,2,3,2,2,2,2,2,2,2,2,2,2,2,2],"legend":["Blank","Floor","Wall","Exit","IceNW","IceNE","Gravel","Ice","IceSE","IceSW","GreenButton","Dirt","BlueButton","ToggleWall"]},"entities":[{"kind":"Player","pos":[12,15]},{"kind":"Chip","pos":[12,7]},{"kind":"Chip","pos":[4,15]},{"kind":"Chip","pos":[20,15]},{"kind":"Chip","pos":[12,23]},{"kind":"Socket","pos":[4,5]},{"kind":"Socket","pos":[20,5]},{"kind":"Socket","pos":[4,25]},{"kind":"Socket","pos":[20,25]},{"kind":"IceSkates","pos":[12,15]},{"kind":"Bug","pos":[5,15],"face_dir":"Down"},{"kind":"Bug","pos":[19,15],"face_dir":"Up"},{"kind":"Tank","pos":[12,4],"face_dir":"Right"},{"kind":"Tank","pos":[1,15],"face_dir":"Up"},{"kind":"Tank","pos":[23,15],"face_dir":"Down"},{"kind":"Tank","pos":[12,26],"face_dir":"Left"},{"kind":"Teeth","pos":[9,12],"face_dir":"Down"},{"kind":"Teeth","pos":[15,12],"face_dir":"Down"},{"kind":"Teeth","pos":[9,18],"face_dir":"Down"},{"kind":"Teeth","pos":[15,18],"face_dir":"Down"},{"kind":"Paramecium","pos":[12,8],"face_dir":"Right"},{"kind":"Paramecium","pos":[12,22],"face_dir":"Left"}],"connections":[]}