{"name":"Chomper Romp","author":"Dale Bryan","password":"WAYT","seed":0,"required_chips":12,"time_limit":600,"map":{"width":32,"height":32,"data":[1,2,3,4,4,1,1,1,1,1,1,1,1,1,5,1,6,7,1,4,1,8,9,10,9,11,9,1,1,1,1,1,1,12,13,14,1,1,1,1,1,1,1,1,1,1,5,10,15,16,1,4,17,18,6,6,6,6,1,12,12,12,12,3,1,12,12,4,4,1,1,1,1,1,1,1,1,1,5,17,4,4,4,4,17,19,20,21,20,20,1,13,13,12,13,16,1,12,13,14,1,1,1,1,1,1,1,1,1,1,5,17,4,1,8,8,1,4,22,4,22,4,1,4,22,4,22,4,1,12,13,4,4,1,1,1,1,1,1,1,1,1,5,17,1,14,14,23,14,4,1,4,1,4,1,4,1,4,1,4,9,1,1,1,1,1,1,1,1,1,1,1,1,1,5,1,1,14,14,10,14,14,1,1,1,1,1,1,1,1,1,1,11,18,20,4,4,1,1,1,1,1,1,1,1,1,5,17,18,14,14,10,14,14,1,1,1,1,1,1,1,1,1,1,9,18,20,14,1,1,1,1,1,1,1,1,1,1,5,17,1,6,14,24,14,14,1,1,1,1,1,1,1,1,1,1,17,18,6,4,4,1,1,1,1,1,1,1,1,1,5,17,17,22,25,24,14,14,1,1,1,1,1,1,1,1,1,1,17,18,20,14,1,1,1,1,1,1,1,1,1,1,5,17,17,1,25,18,14,14,1,1,1,1,1,1,1,1,1,1,17,19,21,4,4,8,8,8,8,8,8,8,8,8,5,17,17,1,1,24,14,14,1,1,1,1,1,1,1,1,1,1,1,22,22,8,8,8,8,8,8,8,8,8,8,8,22,22,17,1,1,1,14,14,1,1,1,1,1,1,1,1,1,1,17,23,22,1,1,1,1,1,1,1,1,1,1,1,22,22,18,1,1,1,14,14,1,1,1,1,1,1,1,1,1,1,17,1,1,1,8,8,8,26,1,1,1,1,27,27,1,1,1,1,1,1,14,14,1,1,1,1,1,1,1,1,1,1,1,22,22,22,8,8,8,18,14,1,1,8,1,27,1,1,1,1,1,17,17,28,28,28,28,28,28,28,28,28,28,28,4,4,4,4,1,1,19,1,22,22,22,17,27,27,27,1,1,1,1,17,17,8,8,8,8,8,1,8,8,8,8,8,22,22,22,22,22,1,22,22,22,22,22,14,14,1,1,1,1,27,27,27,14,8,8,8,1,6,1,1,4,4,4,4,28,28,28,28,28,28,28,28,28,28,28,14,14,1,1,1,1,1,27,1,22,1,1,17,21,22,22,22,8,8,8,1,1,1,1,1,1,1,1,1,1,1,17,17,1,1,27,27,1,1,27,27,1,1,1,1,29,22,22,22,1,1,23,14,1,1,1,1,1,1,1,1,1,1,17,17,1,19,1,27,8,8,1,1,1,1,1,1,1,1,1,1,1,8,8,14,1,1,1,1,1,1,1,1,1,1,17,17,1,27,24,14,8,8,22,22,22,22,22,22,22,22,22,22,22,8,8,1,1,1,1,1,1,1,1,1,1,1,17,17,1,27,24,14,14,5,22,22,22,22,22,22,22,22,22,4,4,18,6,14,1,1,1,1,1,1,1,1,1,1,17,17,1,27,24,14,14,5,1,1,1,1,1,1,1,1,1,1,17,20,21,14,1,1,1,1,1,1,1,1,1,1,17,17,1,27,27,14,14,5,1,1,1,1,1,1,1,1,1,4,4,19,21,14,1,1,1,1,1,1,1,1,1,1,17,17,1,17,19,1,14,5,1,1,1,1,1,1,1,1,1,1,17,20,21,9,1,1,1,1,1,1,1,1,1,1,17,17,1,17,17,21,14,5,1,1,1,1,1,1,1,1,1,4,4,20,21,11,1,1,1,1,1,1,1,1,1,1,17,17,25,23,17,1,1,5,1,1,1,1,1,1,1,1,1,1,1,1,1,9,4,1,4,1,4,1,4,1,4,1,4,17,25,23,17,1,14,5,1,1,1,1,1,1,1,1,1,4,4,13,12,1,4,8,4,8,4,1,4,8,4,8,4,17,25,23,1,4,14,5,1,1,1,1,1,1,1,1,1,1,17,13,12,1,2,13,12,13,13,1,20,20,18,20,6,14,14,1,14,4,14,5,1,1,1,1,1,1,1,1,1,4,4,12,12,1,15,12,12,12,12,1,19,19,19,19,21,14,14,30,14,4,14,5,1,1,1,1,1,1,1,1,1,1,17,13,12,1,1,1,1,1,1,9,11,9,22,22,22,1,22,22,1,4,14,5,1,1,1,1,1,1,1,1,1,4,4,15,16,1],"legend":["Blank","Floor","IceNW","IceNE","Wall","ToggleFloor","ForceW","CloneMachine","ThinWallS","RecessedWall","RedButton","GreenButton","Ice","Fire","ThinWallW","IceSW","IceSE","ThinWallE","ForceS","ForceE","Water","ForceN","ThinWallN","BearTrap","BrownButton","InvisibleWall","CloneBlockN","HiddenWall","ToggleWall","CloneBlockS","Exit"]},"entities":[{"kind":"Teeth","pos":[17,0],"face_dir":"Down"},{"kind":"Teeth","pos":[18,0],"face_dir":"Down"},{"kind":"SuctionBoots","pos":[4,1]},{"kind":"Block","pos":[4,1]},{"kind":"Chip","pos":[4,3]},{"kind":"Block","pos":[4,3]},{"kind":"Chip","pos":[16,4]},{"kind":"Teeth","pos":[19,4],"face_dir":"Down"},{"kind":"Teeth","pos":[22,4],"face_dir":"Down"},{"kind":"Block","pos":[22,4]},{"kind":"Chip","pos":[24,4]},{"kind":"Block","pos":[24,4]},{"kind":"Flippers","pos":[28,4]},{"kind":"Block","pos":[28,4]},{"kind":"Teeth","pos":[30,4],"face_dir":"Down"},{"kind":"Block","pos":[30,4]},{"kind":"Thief","pos":[16,5]},{"kind":"Teeth","pos":[4,7],"face_dir":"Down"},{"kind":"Block","pos":[4,7]},{"kind":"Teeth","pos":[4,9],"face_dir":"Down"},{"kind":"Block","pos":[4,9]},{"kind":"Teeth","pos":[1,12],"face_dir":"Down"},{"kind":"Chip","pos":[5,12]},{"kind":"Bomb","pos":[7,12]},{"kind":"Chip","pos":[3,13]},{"kind":"Chip","pos":[4,15]},{"kind":"Thief","pos":[5,15]},{"kind":"Teeth","pos":[21,15],"face_dir":"Up"},{"kind":"Teeth","pos":[22,15],"face_dir":"Up"},{"kind":"Teeth","pos":[23,15],"face_dir":"Up"},{"kind":"Teeth","pos":[24,15],"face_dir":"Up"},{"kind":"Teeth","pos":[25,15],"face_dir":"Up"},{"kind":"Teeth","pos":[26,15],"face_dir":"Up"},{"kind":"Teeth","pos":[27,15],"face_dir":"Up"},{"kind":"Teeth","pos":[28,15],"face_dir":"Up"},{"kind":"Teeth","pos":[29,15],"face_dir":"Up"},{"kind":"Teeth","pos":[30,15],"face_dir":"Up"},{"kind":"Teeth","pos":[31,15],"face_dir":"Up"},{"kind":"Teeth","pos":[0,16],"face_dir":"Down"},{"kind":"Teeth","pos":[1,16],"face_dir":"Down"},{"kind":"Teeth","pos":[2,16],"face_dir":"Down"},{"kind":"Teeth","pos":[3,16],"face_dir":"Down"},{"kind":"Teeth","pos":[4,16],"face_dir":"Down"},{"kind":"Teeth","pos":[5,16],"face_dir":"Down"},{"kind":"Teeth","pos":[6,16],"face_dir":"Down"},{"kind":"Teeth","pos":[7,16],"face_dir":"Down"},{"kind":"Teeth","pos":[8,16],"face_dir":"Down"},{"kind":"Teeth","pos":[9,16],"face_dir":"Down"},{"kind":"Teeth","pos":[10,16],"face_dir":"Down"},{"kind":"Thief","pos":[26,16]},{"kind":"Chip","pos":[27,16]},{"kind":"Chip","pos":[28,18]},{"kind":"Teeth","pos":[30,18],"face_dir":"Down"},{"kind":"Bomb","pos":[24,19]},{"kind":"Chip","pos":[26,19]},{"kind":"Teeth","pos":[16,21],"face_dir":"Right"},{"kind":"Teeth","pos":[16,22],"face_dir":"Right"},{"kind":"Teeth","pos":[27,22],"face_dir":"Down"},{"kind":"Block","pos":[27,22]},{"kind":"Teeth","pos":[16,23],"face_dir":"Right"},{"kind":"Teeth","pos":[16,24],"face_dir":"Right"},{"kind":"FireBoots","pos":[27,24]},{"kind":"Block","pos":[27,24]},{"kind":"Teeth","pos":[16,25],"face_dir":"Right"},{"kind":"Thief","pos":[15,26]},{"kind":"Teeth","pos":[16,26],"face_dir":"Right"},{"kind":"Teeth","pos":[1,27],"face_dir":"Down"},{"kind":"Block","pos":[1,27]},{"kind":"Teeth","pos":[3,27],"face_dir":"Down"},{"kind":"Block","pos":[3,27]},{"kind":"Chip","pos":[7,27]},{"kind":"Block","pos":[7,27]},{"kind":"IceSkates","pos":[9,27]},{"kind":"Block","pos":[9,27]},{"kind":"Chip","pos":[15,27]},{"kind":"Teeth","pos":[16,27],"face_dir":"Right"},{"kind":"Teeth","pos":[16,28],"face_dir":"Right"},{"kind":"Chip","pos":[27,28]},{"kind":"Block","pos":[27,28]},{"kind":"Socket","pos":[13,29]},{"kind":"Teeth","pos":[16,29],"face_dir":"Right"},{"kind":"Teeth","pos":[16,30],"face_dir":"Right"},{"kind":"Teeth","pos":[27,30],"face_dir":"Down"},{"kind":"Block","pos":[27,30]},{"kind":"Player","pos":[11,31]},{"kind":"Teeth","pos":[16,31],"face_dir":"Right"}],"connections":[{"src":[14,20],"dest":[13,26]},{"src":[14,21],"dest":[13,27]},{"src":[14,22],"dest":[13,28]},{"src":[19,10],"dest":[19,4]},{"src":[19,7],"dest":[30,18]},{"src":[19,8],"dest":[1,12]},{"src":[23,0],"dest":[17,0]},{"src":[15,1],"dest":[17,0]},{"src":[19,5],"dest":[24,18]},{"src":[19,6],"dest":[7,13]}]}