{"name":"ToggleTank","author":"Archie Pusaka","password":"RUJV","seed":3049326818,"required_chips":0,"time_limit":300,"map":{"width":16,"height":31,"data":[0,0,0,0,0,0,0,0,0,0,0,0,0,0,0,0,0,0,0,0,0,0,2,2,2,2,2,0,0,0,0,0,0,0,0,0,0,0,2,2,2,2,2,0,0,0,0,0,0,0,0,0,0,0,2,2,3,2,2,0,0,0,0,0,0,0,0,0,0,0,2,2,4,2,2,0,0,0,0,0,0,0,0,0,0,0,2,2,5,2,2,0,0,0,0,0,0,2,2,2,2,2,2,2,5,2,2,2,2,2,2,0,0,2,2,2,2,2,2,2,5,2,2,2,2,2,2,0,0,2,2,1,1,1,2,1,1,4,1,2,2,2,2,0,0,2,2,1,1,4,2,1,6,2,1,2,2,2,2,0,0,2,2,6,2,1,4,4,1,1,1,2,2,2,2,0,0,2,2,1,1,4,1,2,1,6,1,2,1,2,2,0,0,2,2,1,1,1,1,6,2,4,6,2,1,2,2,0,0,2,2,1,6,2,4,1,1,6,1,2,1,2,2,0,0,2,2,1,1,2,1,2,4,6,1,2,7,2,2,0,0,2,2,1,1,1,1,1,1,1,8,2,9,2,2,0,0,2,2,2,2,2,2,2,2,5,2,2,2,2,2,0,0,2,2,1,1,1,1,1,2,4,4,2,1,2,2,0,0,2,2,1,6,1,4,4,2,1,4,2,1,2,2,0,0,2,2,1,6,6,1,4,6,1,1,2,1,2,2,0,0,2,2,1,6,4,4,1,1,6,1,2,7,2,2,0,0,2,2,1,1,1,1,1,1,1,8,2,9,2,2,0,0,2,2,2,2,2,2,2,2,5,2,2,2,2,2,0,0,2,2,1,1,1,1,2,4,4,4,2,2,2,2,0,0,2,2,1,4,4,1,2,6,1,4,2,1,2,2,0,0,2,2,1,1,4,1,1,6,1,4,2,1,2,2,0,0,2,2,1,1,4,6,6,6,1,4,2,7,2,2,0,0,2,2,1,1,1,1,1,1,1,8,2,9,2,2,0,0,2,2,2,2,2,2,2,2,2,2,2,2,2,2,0,0,2,2,2,2,2,2,2,2,2,2,2,2,2,2,0,0,0,0,0,0,0,0,0,0,0,0,0,0,0,0,0],"legend":["Blank","Floor","Wall","Exit","ToggleWall","Water","ToggleFloor","GreenButton","RedButton","CloneMachine"]},"entities":[{"kind":"Player","pos":[8,27]},{"kind":"Block","pos":[4,9]},{"kind":"Block","pos":[8,13]},{"kind":"Block","pos":[4,14]},{"kind":"Block","pos":[5,18]},{"kind":"Block","pos":[4,26]},{"kind":"Tank","pos":[12,15],"face_dir":"Up"},{"kind":"Tank","pos":[12,21],"face_dir":"Up"},{"kind":"Tank","pos":[12,27],"face_dir":"Up"}],"connections":[{"src":[10,21],"dest":[12,21]},{"src":[10,27],"dest":[12,27]},{"src":[10,15],"dest":[12,15]}]}