{"name":"New Block in Town","author":"Archie Pusaka","hint":"This block is your friend.","password":"LRIM","seed":586444303,"required_chips":4,"time_limit":200,"map":{"width":27,"height":27,"data":[2,2,2,2,2,2,2,2,2,2,2,2,2,2,2,2,2,2,2,2,2,2,2,2,2,2,2,2,2,2,2,2,2,2,2,2,2,2,2,2,2,2,2,2,2,2,2,2,2,2,2,2,2,2,2,2,2,2,2,2,2,2,2,2,2,2,2,2,2,2,3,2,2,2,2,2,2,2,2,2,2,2,2,2,2,2,2,2,2,2,2,2,2,2,2,2,2,1,2,2,2,2,2,2,2,2,2,2,2,2,2,2,2,2,2,2,2,2,2,2,2,2,2,2,4,2,2,2,2,2,2,2,2,2,2,2,2,2,1,1,2,2,2,2,2,2,2,2,2,2,2,5,2,2,2,2,2,2,2,2,2,2,2,2,2,6,1,2,2,2,2,2,2,2,2,2,2,2,5,2,2,2,2,2,2,2,2,2,2,2,2,2,1,1,2,2,2,2,2,2,2,2,2,2,2,5,2,2,2,2,2,2,2,2,2,2,2,2,2,2,1,2,2,2,2,2,2,2,2,2,2,2,5,2,2,2,2,2,2,2,2,2,2,2,2,2,1,1,2,2,2,2,2,2,2,2,2,2,2,5,2,2,2,2,2,2,2,2,2,2,2,2,2,1,5,2,1,1,1,1,1,1,1,1,1,1,1,2,2,2,2,2,2,2,2,2,2,2,2,2,1,5,2,1,7,5,8,1,7,5,5,5,5,1,2,2,2,2,2,2,2,2,2,2,2,2,2,1,5,2,9,10,9,10,9,10,2,2,2,2,5,2,2,2,2,2,2,2,2,2,2,2,2,2,1,5,2,9,10,9,10,9,10,2,2,2,2,5,2,2,2,2,2,2,2,2,2,2,2,2,2,9,10,2,9,10,9,10,9,10,2,2,2,2,5,2,2,2,2,2,2,2,2,2,2,2,2,2,1,5,2,1,11,5,5,5,12,2,2,2,1,1,2,2,2,2,2,2,2,2,2,2,2,2,2,1,5,2,1,1,1,5,1,1,2,2,2,1,5,2,2,2,2,2,2,2,2,2,2,2,2,2,1,5,2,9,7,5,10,5,8,2,2,2,1,5,2,2,2,2,2,2,2,2,2,2,2,2,2,1,5,2,1,5,1,5,1,5,2,2,2,1,5,2,2,2,2,2,2,2,2,2,2,2,2,9,1,10,2,9,5,1,11,10,12,2,2,9,1,10,2,2,2,2,2,2,2,2,2,2,2,2,2,1,5,2,1,5,1,1,1,1,2,2,2,1,5,2,2,2,2,2,2,2,2,2,2,2,2,2,1,5,2,1,11,5,5,5,8,2,2,2,1,1,1,1,1,1,1,4,13,3,2,2,2,2,2,1,5,2,2,2,2,2,1,5,2,2,2,2,2,2,2,2,2,2,2,2,2,2,2,2,2,2,1,5,14,1,1,1,9,1,10,2,2,2,2,2,2,2,2,2,2,2,2,2,2,2,2,2,2,1,1,5,5,5,5,5,5,12,2,2,2,2,2,2,2,2,2,2,2,2,2,2,2,2,2,2,2,2,2,2,2,2,2,2,2,2,2,2,2,2,2,2,2,2,2,2,2,2,2,2,2,2,2,2,2,2,2,2,2,2,2,2,2,2,2,2,2,2,2,2,2,2,2,2,2,2,2],"legend":["Blank","Floor","Wall","Exit","Water","Ice","Hint","IceNW","IceNE","BrownButton","BearTrap","IceSW","IceSE","HiddenWall","RecessedWall"]},"entities":[{"kind":"Player","pos":[3,9]},{"kind":"Chip","pos":[16,11]},{"kind":"Chip","pos":[10,18]},{"kind":"Chip","pos":[16,21]},{"kind":"Chip","pos":[4,24]},{"kind":"Socket","pos":[16,3]},{"kind":"Socket","pos":[17,21]},{"kind":"Block","pos":[4,8]},{"kind":"IceSkates","pos":[18,21]}],"connections":[{"src":[3,14],"dest":[4,14]},{"src":[2,19],"dest":[4,19]},{"src":[9,23],"dest":[11,23]},{"src":[6,19],"dest":[10,19]},{"src":[6,17],"dest":[9,17]},{"src":[6,14],"dest":[7,14]},{"src":[6,13],"dest":[7,13]},{"src":[6,12],"dest":[7,12]},{"src":[8,12],"dest":[9,12]},{"src":[8,13],"dest":[9,13]},{"src":[8,14],"dest":[9,14]},{"src":[10,14],"dest":[11,14]},{"src":[10,13],"dest":[11,13]},{"src":[10,12],"dest":[11,12]},{"src":[14,19],"dest":[16,19]}]}