{"name":"Design Swap","author":"Josh Lee","password":"VGJF","seed":0,"time":500,"chips":32,"map":{"width":32,"height":32,"data":[2,2,2,2,2,2,2,2,2,2,2,2,2,2,2,2,2,2,2,2,2,2,2,2,2,2,2,2,2,2,2,2,2,1,3,1,4,1,1,1,1,1,1,1,4,1,3,1,1,3,1,4,1,1,1,1,1,1,1,4,1,3,1,2,2,3,2,1,1,5,6,6,6,6,6,7,1,1,2,8,8,2,1,1,9,9,9,9,9,9,9,1,1,2,3,2,2,1,1,2,1,1,10,7,1,5,10,1,1,2,3,3,3,3,2,1,1,9,9,1,9,9,1,1,2,1,1,2,2,11,1,1,2,1,1,10,10,10,1,1,2,3,3,3,3,3,3,2,1,1,9,9,9,1,1,2,1,1,12,2,2,1,2,1,1,2,1,1,10,1,1,2,3,3,3,3,3,3,3,3,2,1,1,9,1,1,2,1,1,2,1,2,2,1,2,2,1,1,2,1,1,1,2,3,3,3,3,3,3,3,3,3,3,2,1,1,1,2,1,1,2,2,1,2,2,1,1,2,2,1,1,2,2,2,3,3,3,3,3,1,1,3,3,3,3,3,2,2,2,1,1,2,2,13,1,2,2,1,1,14,2,2,1,2,2,1,3,3,3,3,1,1,1,1,3,3,3,3,2,2,2,1,2,2,15,1,1,2,2,1,2,2,2,1,1,2,2,2,3,3,3,3,3,1,1,3,3,3,3,3,2,1,2,1,1,2,2,2,1,2,2,1,2,2,1,1,2,16,16,16,2,3,3,3,3,3,3,3,3,3,3,2,16,16,16,2,1,1,2,2,1,2,2,1,2,1,1,2,16,16,16,16,16,2,3,3,3,3,3,3,3,3,2,16,16,16,16,16,2,1,1,2,1,2,2,11,1,1,2,16,16,16,16,16,16,16,2,3,3,3,3,3,3,2,16,16,16,16,16,16,16,2,1,1,12,2,2,1,1,2,16,16,16,16,16,16,16,16,16,2,3,3,3,3,2,16,16,16,16,16,16,16,16,16,2,1,1,2,2,3,2,16,16,16,16,16,1,16,16,16,16,16,2,1,1,2,16,16,16,16,16,1,16,16,16,16,16,2,3,2,2,1,17,16,16,16,16,1,1,1,16,16,16,16,1,1,1,1,16,16,16,16,1,1,1,16,16,16,16,18,1,2,2,1,17,16,16,16,16,1,1,1,16,16,16,16,1,1,1,1,16,16,16,16,1,1,1,16,16,16,16,18,1,2,2,3,2,16,16,16,16,16,1,16,16,16,16,16,2,1,1,2,16,16,16,16,16,1,16,16,16,16,16,2,3,2,2,1,1,2,16,16,16,16,16,16,16,16,16,2,3,3,3,3,2,16,16,16,16,16,16,16,16,16,2,1,1,2,2,11,1,1,2,16,16,16,16,16,16,16,2,3,3,3,3,3,3,2,16,16,16,16,16,16,16,2,1,1,12,2,2,1,2,1,1,2,16,16,16,16,16,2,3,3,3,3,3,3,3,3,2,16,16,16,16,16,2,1,1,19,12,2,2,1,2,2,1,1,2,16,16,16,2,3,3,3,3,3,3,3,3,3,3,2,16,16,16,2,1,1,19,19,12,2,2,1,2,2,2,1,1,2,1,2,3,3,3,3,3,1,1,3,3,3,3,3,2,2,2,1,1,19,19,19,12,2,2,1,20,21,2,2,1,2,2,2,3,3,3,3,1,1,1,1,3,3,3,3,2,2,2,1,22,19,23,19,12,2,2,1,2,2,2,1,1,2,2,2,3,3,3,3,3,1,1,3,3,3,3,3,2,2,2,1,1,19,19,19,12,2,2,1,2,2,1,1,2,1,1,1,2,3,3,3,3,3,3,3,3,3,3,2,1,4,1,2,1,1,19,19,12,2,2,1,2,1,1,2,1,1,24,1,1,2,3,3,3,3,3,3,3,3,2,1,25,26,1,1,2,1,1,19,12,2,2,11,1,1,2,1,1,24,24,24,1,1,2,3,3,3,3,3,3,2,1,25,26,26,26,1,1,2,1,1,12,2,2,1,1,2,1,1,24,24,1,24,24,1,1,2,3,3,3,3,2,1,25,26,26,26,26,26,1,1,2,1,1,2,2,3,2,1,1,24,24,24,24,24,24,24,1,1,2,27,27,2,1,11,28,26,26,26,26,26,26,12,1,2,3,2,2,1,3,1,29,1,1,1,1,1,1,1,29,1,3,1,1,3,1,29,29,29,29,29,29,29,29,29,1,3,1,2,2,2,2,2,2,2,2,2,2,2,2,2,2,2,2,2,2,2,2,2,2,2,2,2,2,2,2,2,2,2,2,2],"legend":["Blank","Floor","Wall","Gravel","PanelS","ForceE","ForceN","ForceW","BlueLock","Water","ForceS","PanelE","PanelW","CloneMachine","Exit","BlueButton","Dirt","RedLock","YellowLock","ToggleWall","BearTrap","RedButton","RecessedWall","BrownButton","Fire","PanelSE","Ice","GreenLock","GreenButton","PanelN"]},"entities":[{"kind":"RedKey","pos":[30,1]},{"kind":"IceSkates","pos":[8,3]},{"kind":"Paramecium","pos":[12,3],"face_dir":"Up"},{"kind":"Bug","pos":[19,3],"face_dir":"Up"},{"kind":"FireBoots","pos":[23,3]},{"kind":"Paramecium","pos":[11,4],"face_dir":"Up"},{"kind":"Bug","pos":[20,4],"face_dir":"Up"},{"kind":"Paramecium","pos":[10,5],"face_dir":"Up"},{"kind":"Bug","pos":[21,5],"face_dir":"Up"},{"kind":"Bug","pos":[1,6],"face_dir":"Up"},{"kind":"Paramecium","pos":[30,6],"face_dir":"Up"},{"kind":"Chip","pos":[15,7]},{"kind":"Chip","pos":[16,7]},{"kind":"Block","pos":[29,7],"face_dir":"Down"},{"kind":"Bug","pos":[1,8],"face_dir":"Up"},{"kind":"Tank","pos":[2,8],"face_dir":"Down"},{"kind":"GreenKey","pos":[9,8]},{"kind":"Chip","pos":[14,8]},{"kind":"Chip","pos":[15,8]},{"kind":"Chip","pos":[16,8]},{"kind":"Chip","pos":[17,8]},{"kind":"Bomb","pos":[29,8]},{"kind":"Paramecium","pos":[30,8],"face_dir":"Up"},{"kind":"Chip","pos":[15,9]},{"kind":"Chip","pos":[16,9]},{"kind":"BlueKey","pos":[23,9]},{"kind":"Bug","pos":[1,10],"face_dir":"Up"},{"kind":"Paramecium","pos":[30,10],"face_dir":"Up"},{"kind":"Chip","pos":[8,14]},{"kind":"Socket","pos":[15,14]},{"kind":"Socket","pos":[16,14]},{"kind":"Chip","pos":[23,14]},{"kind":"Chip","pos":[7,15]},{"kind":"Chip","pos":[8,15]},{"kind":"Chip","pos":[9,15]},{"kind":"Socket","pos":[14,15]},{"kind":"Flippers","pos":[15,15]},{"kind":"Socket","pos":[17,15]},{"kind":"Chip","pos":[22,15]},{"kind":"Chip","pos":[23,15]},{"kind":"Chip","pos":[24,15]},{"kind":"Chip","pos":[7,16]},{"kind":"Chip","pos":[8,16]},{"kind":"Chip","pos":[9,16]},{"kind":"Socket","pos":[14,16]},{"kind":"Socket","pos":[17,16]},{"kind":"Chip","pos":[22,16]},{"kind":"Chip","pos":[23,16]},{"kind":"Chip","pos":[24,16]},{"kind":"Chip","pos":[8,17]},{"kind":"Socket","pos":[15,17]},{"kind":"Socket","pos":[16,17]},{"kind":"Chip","pos":[23,17]},{"kind":"YellowKey","pos":[8,22]},{"kind":"Chip","pos":[15,22]},{"kind":"Chip","pos":[16,22]},{"kind":"Chip","pos":[14,23]},{"kind":"Chip","pos":[15,23]},{"kind":"Chip","pos":[16,23]},{"kind":"Chip","pos":[17,23]},{"kind":"Block","pos":[26,23]},{"kind":"Chip","pos":[15,24]},{"kind":"Chip","pos":[16,24]},{"kind":"Paramecium","pos":[5,25],"face_dir":"Up"},{"kind":"Bug","pos":[26,25],"face_dir":"Up"},{"kind":"Paramecium","pos":[4,26],"face_dir":"Up"},{"kind":"Paramecium","pos":[25,26],"face_dir":"Up"},{"kind":"Bug","pos":[27,26],"face_dir":"Up"},{"kind":"Paramecium","pos":[3,27],"face_dir":"Up"},{"kind":"Paramecium","pos":[26,27],"face_dir":"Up"},{"kind":"Bug","pos":[28,27],"face_dir":"Up"},{"kind":"SuctionBoots","pos":[8,28]},{"kind":"Paramecium","pos":[27,28],"face_dir":"Up"},{"kind":"Player","pos":[1,30]},{"kind":"Bug","pos":[8,30],"face_dir":"Left"},{"kind":"Bug","pos":[10,30],"face_dir":"Left"},{"kind":"Bug","pos":[12,30],"face_dir":"Left"}],"connections":[{"src":[28,23],"dest":[2,23]},{"src":[3,23],"dest":[29,7]}]}
