{"name":"Ages Beyond","author":"Jeffrey Bardon","password":"WRLH","required_chips":24,"time_limit":300,"map":{"width":22,"height":30,"data":[2,2,2,2,2,2,2,2,2,2,2,2,2,2,2,2,2,2,2,2,2,2,2,2,2,2,2,2,2,2,2,2,2,2,2,2,2,2,1,2,2,2,2,2,2,2,2,2,2,2,2,2,2,2,2,2,2,3,3,1,3,3,3,4,2,2,2,2,2,2,2,2,2,2,2,2,2,2,2,5,2,2,5,2,2,4,2,2,2,2,2,2,2,2,2,2,2,2,2,2,2,5,2,4,6,6,2,4,1,2,2,2,2,2,2,2,2,1,5,4,5,1,6,5,3,4,1,3,3,4,2,2,2,2,2,2,2,1,2,2,2,2,5,1,2,5,2,3,3,5,2,4,2,2,2,2,1,1,1,1,1,1,1,2,1,1,3,5,2,2,5,2,2,4,2,2,2,2,1,2,2,7,2,2,1,2,1,1,2,5,6,6,6,1,6,6,2,2,2,2,1,2,1,1,1,2,1,2,1,1,2,2,2,2,2,1,2,2,2,2,2,1,1,7,1,1,1,7,1,7,1,7,7,7,1,2,2,2,2,2,2,2,2,2,1,2,1,1,1,2,1,2,1,7,2,2,2,2,2,2,2,2,2,2,2,2,1,2,2,1,2,2,1,2,1,1,2,1,1,8,1,8,1,1,2,2,2,2,1,1,1,1,1,1,1,2,1,1,2,1,2,2,1,2,2,1,1,2,2,2,2,2,2,2,2,2,2,2,9,1,2,8,2,10,10,10,2,8,2,2,2,2,2,2,2,2,2,1,11,11,11,12,1,1,1,1,1,1,1,1,2,2,2,2,2,2,2,2,2,2,2,2,11,12,2,8,2,1,1,10,2,8,2,2,2,2,1,1,1,1,1,1,1,2,1,1,2,1,2,2,1,2,2,1,2,2,2,2,1,2,2,1,2,2,1,2,1,1,2,1,1,8,1,8,1,1,2,2,2,2,1,2,1,1,1,2,1,2,1,1,2,2,2,2,2,2,2,2,2,2,2,2,1,1,1,1,1,1,1,1,1,1,1,1,13,2,2,2,2,2,2,2,2,2,1,2,1,1,1,2,1,2,1,1,2,2,2,2,2,2,2,2,2,2,2,2,1,2,2,1,2,2,1,2,1,1,2,1,14,15,1,14,16,1,2,2,2,2,1,1,1,1,1,1,1,2,1,1,2,16,2,2,1,2,2,15,2,2,2,2,2,2,2,2,2,2,2,2,1,1,2,14,2,1,1,1,2,16,2,2,2,2,2,2,2,2,2,1,17,17,17,1,1,1,1,1,1,1,1,1,2,2,2,2,2,2,2,2,2,2,2,2,17,1,2,15,2,1,1,1,2,14,2,2,2,2,2,2,2,2,2,2,2,2,2,2,2,15,2,2,1,2,2,14,2,2,2,2,2,2,2,2,2,2,2,2,2,2,2,1,16,15,1,16,16,1,2,2,2,2,2,2,2,2,2,2,2,2,2,2,2,2,2,2,2,2,2,2,2,2],"legend":["Blank","Floor","Wall","ForceE","ForceS","ForceN","ForceW","Gravel","RecessedWall","ThinWallS","BrownButton","BearTrap","ThinWallW","Exit","RedLock","BlueLock","YellowLock","GreenLock"]},"entities":[{"kind":"Player","pos":[11,15]},{"kind":"Chip","pos":[16,1]},{"kind":"Chip","pos":[20,4]},{"kind":"Chip","pos":[7,5]},{"kind":"Chip","pos":[16,5]},{"kind":"Chip","pos":[5,6]},{"kind":"Chip","pos":[17,9]},{"kind":"Chip","pos":[1,10]},{"kind":"Chip","pos":[5,10]},{"kind":"Chip","pos":[14,10]},{"kind":"Chip","pos":[5,12]},{"kind":"Chip","pos":[13,12]},{"kind":"Chip","pos":[19,12]},{"kind":"Chip","pos":[7,15]},{"kind":"Chip","pos":[3,17]},{"kind":"Chip","pos":[2,18]},{"kind":"Chip","pos":[13,18]},{"kind":"Chip","pos":[19,18]},{"kind":"Chip","pos":[5,21]},{"kind":"Chip","pos":[8,22]},{"kind":"Chip","pos":[13,22]},{"kind":"Chip","pos":[19,22]},{"kind":"Chip","pos":[7,25]},{"kind":"Chip","pos":[13,28]},{"kind":"Chip","pos":[19,28]},{"kind":"Socket","pos":[2,17]},{"kind":"Socket","pos":[5,18]},{"kind":"Socket","pos":[5,20]},{"kind":"Socket","pos":[11,20]},{"kind":"Socket","pos":[12,20]},{"kind":"Socket","pos":[13,20]},{"kind":"Socket","pos":[6,21]},{"kind":"Socket","pos":[8,21]},{"kind":"Socket","pos":[11,21]},{"kind":"Socket","pos":[5,22]},{"kind":"Block","pos":[16,13]},{"kind":"Block","pos":[20,13]},{"kind":"Block","pos":[14,15]},{"kind":"Block","pos":[18,15]},{"kind":"Block","pos":[16,17]},{"kind":"BlueKey","pos":[15,24]},{"kind":"BlueKey","pos":[17,25]},{"kind":"BlueKey","pos":[16,26]},{"kind":"RedKey","pos":[17,24]},{"kind":"RedKey","pos":[15,26]},{"kind":"GreenKey","pos":[16,25]},{"kind":"YellowKey","pos":[16,24]},{"kind":"YellowKey","pos":[15,25]},{"kind":"YellowKey","pos":[17,26]},{"kind":"Bug","pos":[8,9],"face_dir":"Up"},{"kind":"FireBall","pos":[2,7],"face_dir":"Down"},{"kind":"Glider","pos":[4,13],"face_dir":"Right"},{"kind":"Paramecium","pos":[4,10],"face_dir":"Up"}],"connections":[{"src":[15,14],"dest":[8,15]},{"src":[16,14],"dest":[9,15]},{"src":[17,14],"dest":[10,15]},{"src":[17,16],"dest":[10,16]}]}